<?xml version="1.0" encoding="UTF-8" standalone="yes"?>
<comments xmlns="http://schemas.openxmlformats.org/spreadsheetml/2006/main"><authors><author>Snoeyink, Jack S.</author><author>Loera, Maria</author></authors><commentList><comment ref="AH3" authorId="0" shapeId="0"><text><r><rPr><b/><sz val="9"/><color indexed="81"/><rFont val="Tahoma"/><family val="2"/></rPr><t>Snoeyink, Jack S.:</t></r><r><rPr><sz val="9"/><color indexed="81"/><rFont val="Tahoma"/><family val="2"/></rPr><t xml:space="preserve">
Total postdoc $ in all project budgets.
</t></r></text></comment><comment ref="AV3" authorId="1" shapeId="0"><text><r><rPr><b/><sz val="9"/><color indexed="81"/><rFont val="Tahoma"/><family val="2"/></rPr><t>Loera, Maria:</t></r><r><rPr><sz val="9"/><color indexed="81"/><rFont val="Tahoma"/><family val="2"/></rPr><t xml:space="preserve">
N/A: Project before 01/15/2017
Missing: COA document was not provided.
Need Permission: No permission to access this information, contact IT help.</t></r></text></comment></commentList></comments>